Workbook

Sheet Read me
A1: Manual check case: IJzertoren Memorial Square (real project)
A2: Real project from the DSLIB database (Ghent University): Batselier, J. & Vanhoucke, M. (2015), International Journal of Project Management 33(3), 697-710. Project C2015-33, Belgium, 2013-14, EUR.
A3: Baseline 14-Oct-2013 to 20-Dec-2013; 5 month-end progress reports; finished on 28-Feb-2014, about 2 months late and 4.8 % over budget.
A4: The 12 real activities are grouped into 4 work packages. Budgets, PV and EV are sums of the activity values recorded in ProTrack; % values are rounded to 2 decimals so everything can be checked with a calculator.
A6: Sheets
A7: Inputs - the 20 input rows (5 dates x 4 work packages), identical to the upload file C2015-33_ijzertoren_manual_check_work_packages.csv. Blue = typed input.
A8: Work package calculation - PV, EV, AC, CV, SV, CPI, SPI and status for every work package and date.
A9: Project calculation - every dashboard metric for every date: CPI, SPI, EAC (A, B, C), ETC, VAC, TCPI, health. Rows 3 and 4 (30-Nov and 31-Dec) are the two benchmark periods worked by hand in the validation report.
A10: Forecast check - each forecast compared with the real final cost (known because the project is complete).
A11: Feature tour - which dashboard feature to show at which date, using this data.
A12: Settings - health thresholds (same defaults as the dashboard sidebar) and an example for method D.
A14: How to check the app: upload the CSV (or press 'Manual check case' on the dashboard home screen), pick a reporting date in the sidebar, and compare each figure with the same row here. All cells in black are formulas - click any cell to see how it is calculated.

Sheet Inputs
A1: Period | B1: Reporting date | C1: WP ID | D1: Work package | E1: Budget | F1: Planned progress % | G1: Actual progress % | H1: AC cumulative
A2: 1 | B2: 41578 | C2: WP1 | D2: Demolition and sewerage | E2: 49231.67 | F2: 100 | G2: 61.54 | H2: 28328.72
A3: 1 | B3: 41578 | C3: WP2 | D3: Earthworks and foundations | E3: 58025.66 | F3: 20.67 | G3: 5.17 | H3: 995.46
A4: 1 | B4: 41578 | C4: WP3 | D4: Kerbs, paving and concrete | E4: 78356.7 | F4: 0 | G4: 0 | H4: 0
A5: 1 | B5: 41578 | C5: WP4 | D5: Finishing: street furniture and signage | E5: 28803.68 | F5: 0 | G5: 0 | H5: 0
A6: 2 | B6: 41608 | C6: WP1 | D6: Demolition and sewerage | E6: 49231.67 | F6: 100 | G6: 92.31 | H6: 38459.62
A7: 2 | B7: 41608 | C7: WP2 | D7: Earthworks and foundations | E7: 58025.66 | F7: 100 | G7: 32.64 | H7: 50759.94
A8: 2 | B8: 41608 | C8: WP3 | D8: Kerbs, paving and concrete | E8: 78356.7 | F8: 5.75 | G8: 12.4 | H8: 10271.32
A9: 2 | B9: 41608 | C9: WP4 | D9: Finishing: street furniture and signage | E9: 28803.68 | F9: 0 | G9: 19.74 | H9: 6201.39
A10: 3 | B10: 41639 | C10: WP1 | D10: Demolition and sewerage | E10: 49231.67 | F10: 100 | G10: 100 | H10: 39821.67
A11: 3 | B11: 41639 | C11: WP2 | D11: Earthworks and foundations | E11: 58025.66 | F11: 100 | G11: 58.03 | H11: 69412.98
A12: 3 | B12: 41639 | C12: WP3 | D12: Kerbs, paving and concrete | E12: 78356.7 | F12: 100 | G12: 22.27 | H12: 40197.69
A13: 3 | B13: 41639 | C13: WP4 | D13: Finishing: street furniture and signage | E13: 28803.68 | F13: 100 | G13: 39.49 | H13: 7162.11
... A21: 5 | B21: 41698 | C21: WP4 | D21: Finishing: street furniture and signage | E21: 28803.68 | F21: 100 | G21: 100 | H21: 26779.64

Sheet Work package calculation
A1: Period | B1: Status date | C1: WP ID | D1: Work package | E1: Budget | F1: Planned % | G1: Actual % | H1: PV | I1: EV | J1: AC | K1: CV | L1: SV | M1: CPI | N1: SPI | O1: Status
A2: =Inputs!A2 -> 1 | B2: =Inputs!B2 -> 41578 | C2: =Inputs!C2 -> WP1 | D2: =Inputs!D2 -> Demolition and sewerage | E2: =Inputs!E2 -> 49231.67 | F2: =Inputs!F2 -> 100 | G2: =Inputs!G2 -> 61.54 | H2: =E2*F2/100 -> 49231.67 | I2: =E2*G2/100 -> 30297.17 | J2: =Inputs!H2 -> 28328.72 | K2: =I2-J2 -> 1968.4497 | L2: =I2-H2 -> -18934.5 | M2: =IF(J2>0,I2/J2,"Undefined") -> 1.069486 | N2: =IF(H2>0,I2/H2,"Undefined") -> 0.6154 | O2: =IF(AND(H2<=0.005,I2<=0.005,J2<=0.005),"Not started",IF(OR(ISTEXT(M2),ISTEXT(N2)),"Insufficient data",IF(MIN(M2,N2)<Settings!$B$3,"Critical",IF(MIN(M2,N2)<Settings!$B$2,"Warning","Favourable")))) -> Critical
A3: =Inputs!A3 -> 1 | B3: =Inputs!B3 -> 41578 | C3: =Inputs!C3 -> WP2 | D3: =Inputs!D3 -> Earthworks and foundations | E3: =Inputs!E3 -> 58025.66 | F3: =Inputs!F3 -> 20.67 | G3: =Inputs!G3 -> 5.17 | H3: =E3*F3/100 -> 11993.904 | I3: =E3*G3/100 -> 2999.9266 | J3: =Inputs!H3 -> 995.46 | K3: =I3-J3 -> 2004.4666 | L3: =I3-H3 -> -8993.9773 | M3: =IF(J3>0,I3/J3,"Undefined") -> 3.0136084 | N3: =IF(H3>0,I3/H3,"Undefined") -> 0.25012095 | O3: =IF(AND(H3<=0.005,I3<=0.005,J3<=0.005),"Not started",IF(OR(ISTEXT(M3),ISTEXT(N3)),"Insufficient data",IF(MIN(M3,N3)<Settings!$B$3,"Critical",IF(MIN(M3,N3)<Settings!$B$2,"Warning","Favourable")))) -> Critical
A4: =Inputs!A4 -> 1 | B4: =Inputs!B4 -> 41578 | C4: =Inputs!C4 -> WP3 | D4: =Inputs!D4 -> Kerbs, paving and concrete | E4: =Inputs!E4 -> 78356.7 | F4: =Inputs!F4 -> 0 | G4: =Inputs!G4 -> 0 | H4: =E4*F4/100 -> 0 | I4: =E4*G4/100 -> 0 | J4: =Inputs!H4 -> 0 | K4: =I4-J4 -> 0 | L4: =I4-H4 -> 0 | M4: =IF(J4>0,I4/J4,"Undefined") -> Undefined | N4: =IF(H4>0,I4/H4,"Undefined") -> Undefined | O4: =IF(AND(H4<=0.005,I4<=0.005,J4<=0.005),"Not started",IF(OR(ISTEXT(M4),ISTEXT(N4)),"Insufficient data",IF(MIN(M4,N4)<Settings!$B$3,"Critical",IF(MIN(M4,N4)<Settings!$B$2,"Warning","Favourable")))) -> Not started
A5: =Inputs!A5 -> 1 | B5: =Inputs!B5 -> 41578 | C5: =Inputs!C5 -> WP4 | D5: =Inputs!D5 -> Finishing: street furniture and signage | E5: =Inputs!E5 -> 28803.68 | F5: =Inputs!F5 -> 0 | G5: =Inputs!G5 -> 0 | H5: =E5*F5/100 -> 0 | I5: =E5*G5/100 -> 0 | J5: =Inputs!H5 -> 0 | K5: =I5-J5 -> 0 | L5: =I5-H5 -> 0 | M5: =IF(J5>0,I5/J5,"Undefined") -> Undefined | N5: =IF(H5>0,I5/H5,"Undefined") -> Undefined | O5: =IF(AND(H5<=0.005,I5<=0.005,J5<=0.005),"Not started",IF(OR(ISTEXT(M5),ISTEXT(N5)),"Insufficient data",IF(MIN(M5,N5)<Settings!$B$3,"Critical",IF(MIN(M5,N5)<Settings!$B$2,"Warning","Favourable")))) -> Not started
A6: =Inputs!A6 -> 2 | B6: =Inputs!B6 -> 41608 | C6: =Inputs!C6 -> WP1 | D6: =Inputs!D6 -> Demolition and sewerage | E6: =Inputs!E6 -> 49231.67 | F6: =Inputs!F6 -> 100 | G6: =Inputs!G6 -> 92.31 | H6: =E6*F6/100 -> 49231.67 | I6: =E6*G6/100 -> 45445.755 | J6: =Inputs!H6 -> 38459.62 | K6: =I6-J6 -> 6986.1346 | L6: =I6-H6 -> -3785.9154 | M6: =IF(J6>0,I6/J6,"Undefined") -> 1.1816486 | N6: =IF(H6>0,I6/H6,"Undefined") -> 0.9231 | O6: =IF(AND(H6<=0.005,I6<=0.005,J6<=0.005),"Not started",IF(OR(ISTEXT(M6),ISTEXT(N6)),"Insufficient data",IF(MIN(M6,N6)<Settings!$B$3,"Critical",IF(MIN(M6,N6)<Settings!$B$2,"Warning","Favourable")))) -> Warning
A7: =Inputs!A7 -> 2 | B7: =Inputs!B7 -> 41608 | C7: =Inputs!C7 -> WP2 | D7: =Inputs!D7 -> Earthworks and foundations | E7: =Inputs!E7 -> 58025.66 | F7: =Inputs!F7 -> 100 | G7: =Inputs!G7 -> 32.64 | H7: =E7*F7/100 -> 58025.66 | I7: =E7*G7/100 -> 18939.575 | J7: =Inputs!H7 -> 50759.94 | K7: =I7-J7 -> -31820.365 | L7: =I7-H7 -> -39086.085 | M7: =IF(J7>0,I7/J7,"Undefined") -> 0.37312052 | N7: =IF(H7>0,I7/H7,"Undefined") -> 0.3264 | O7: =IF(AND(H7<=0.005,I7<=0.005,J7<=0.005),"Not started",IF(OR(ISTEXT(M7),ISTEXT(N7)),"Insufficient data",IF(MIN(M7,N7)<Settings!$B$3,"Critical",IF(MIN(M7,N7)<Settings!$B$2,"Warning","Favourable")))) -> Critical
A8: =Inputs!A8 -> 2 | B8: =Inputs!B8 -> 41608 | C8: =Inputs!C8 -> WP3 | D8: =Inputs!D8 -> Kerbs, paving and concrete | E8: =Inputs!E8 -> 78356.7 | F8: =Inputs!F8 -> 5.75 | G8: =Inputs!G8 -> 12.4 | H8: =E8*F8/100 -> 4505.5103 | I8: =E8*G8/100 -> 9716.2308 | J8: =Inputs!H8 -> 10271.32 | K8: =I8-J8 -> -555.0892 | L8: =I8-H8 -> 5210.7206 | M8: =IF(J8>0,I8/J8,"Undefined") -> 0.94595736 | N8: =IF(H8>0,I8/H8,"Undefined") -> 2.1565217 | O8: =IF(AND(H8<=0.005,I8<=0.005,J8<=0.005),"Not started",IF(OR(ISTEXT(M8),ISTEXT(N8)),"Insufficient data",IF(MIN(M8,N8)<Settings!$B$3,"Critical",IF(MIN(M8,N8)<Settings!$B$2,"Warning","Favourable")))) -> Warning
A9: =Inputs!A9 -> 2 | B9: =Inputs!B9 -> 41608 | C9: =Inputs!C9 -> WP4 | D9: =Inputs!D9 -> Finishing: street furniture and signage | E9: =Inputs!E9 -> 28803.68 | F9: =Inputs!F9 -> 0 | G9: =Inputs!G9 -> 19.74 | H9: =E9*F9/100 -> 0 | I9: =E9*G9/100 -> 5685.8464 | J9: =Inputs!H9 -> 6201.39 | K9: =I9-J9 -> -515.54357 | L9: =I9-H9 -> 5685.8464 | M9: =IF(J9>0,I9/J9,"Undefined") -> 0.91686645 | N9: =IF(H9>0,I9/H9,"Undefined") -> Undefined | O9: =IF(AND(H9<=0.005,I9<=0.005,J9<=0.005),"Not started",IF(OR(ISTEXT(M9),ISTEXT(N9)),"Insufficient data",IF(MIN(M9,N9)<Settings!$B$3,"Critical",IF(MIN(M9,N9)<Settings!$B$2,"Warning","Favourable")))) -> Insufficient data
A10: =Inputs!A10 -> 3 | B10: =Inputs!B10 -> 41639 | C10: =Inputs!C10 -> WP1 | D10: =Inputs!D10 -> Demolition and sewerage | E10: =Inputs!E10 -> 49231.67 | F10: =Inputs!F10 -> 100 | G10: =Inputs!G10 -> 100 | H10: =E10*F10/100 -> 49231.67 | I10: =E10*G10/100 -> 49231.67 | J10: =Inputs!H10 -> 39821.67 | K10: =I10-J10 -> 9410 | L10: =I10-H10 -> 0 | M10: =IF(J10>0,I10/J10,"Undefined") -> 1.2363035 | N10: =IF(H10>0,I10/H10,"Undefined") -> 1 | O10: =IF(AND(H10<=0.005,I10<=0.005,J10<=0.005),"Not started",IF(OR(ISTEXT(M10),ISTEXT(N10)),"Insufficient data",IF(MIN(M10,N10)<Settings!$B$3,"Critical",IF(MIN(M10,N10)<Settings!$B$2,"Warning","Favourable")))) -> Favourable
A11: =Inputs!A11 -> 3 | B11: =Inputs!B11 -> 41639 | C11: =Inputs!C11 -> WP2 | D11: =Inputs!D11 -> Earthworks and foundations | E11: =Inputs!E11 -> 58025.66 | F11: =Inputs!F11 -> 100 | G11: =Inputs!G11 -> 58.03 | H11: =E11*F11/100 -> 58025.66 | I11: =E11*G11/100 -> 33672.29 | J11: =Inputs!H11 -> 69412.98 | K11: =I11-J11 -> -35740.69 | L11: =I11-H11 -> -24353.37 | M11: =IF(J11>0,I11/J11,"Undefined") -> 0.48510078 | N11: =IF(H11>0,I11/H11,"Undefined") -> 0.5803 | O11: =IF(AND(H11<=0.005,I11<=0.005,J11<=0.005),"Not started",IF(OR(ISTEXT(M11),ISTEXT(N11)),"Insufficient data",IF(MIN(M11,N11)<Settings!$B$3,"Critical",IF(MIN(M11,N11)<Settings!$B$2,"Warning","Favourable")))) -> Critical
A12: =Inputs!A12 -> 3 | B12: =Inputs!B12 -> 41639 | C12: =Inputs!C12 -> WP3 | D12: =Inputs!D12 -> Kerbs, paving and concrete | E12: =Inputs!E12 -> 78356.7 | F12: =Inputs!F12 -> 100 | G12: =Inputs!G12 -> 22.27 | H12: =E12*F12/100 -> 78356.7 | I12: =E12*G12/100 -> 17450.037 | J12: =Inputs!H12 -> 40197.69 | K12: =I12-J12 -> -22747.653 | L12: =I12-H12 -> -60906.663 | M12: =IF(J12>0,I12/J12,"Undefined") -> 0.43410547 | N12: =IF(H12>0,I12/H12,"Undefined") -> 0.2227 | O12: =IF(AND(H12<=0.005,I12<=0.005,J12<=0.005),"Not started",IF(OR(ISTEXT(M12),ISTEXT(N12)),"Insufficient data",IF(MIN(M12,N12)<Settings!$B$3,"Critical",IF(MIN(M12,N12)<Settings!$B$2,"Warning","Favourable")))) -> Critical
A13: =Inputs!A13 -> 3 | B13: =Inputs!B13 -> 41639 | C13: =Inputs!C13 -> WP4 | D13: =Inputs!D13 -> Finishing: street furniture and signage | E13: =Inputs!E13 -> 28803.68 | F13: =Inputs!F13 -> 100 | G13: =Inputs!G13 -> 39.49 | H13: =E13*F13/100 -> 28803.68 | I13: =E13*G13/100 -> 11374.573 | J13: =Inputs!H13 -> 7162.11 | K13: =I13-J13 -> 4212.4632 | L13: =I13-H13 -> -17429.107 | M13: =IF(J13>0,I13/J13,"Undefined") -> 1.5881595 | N13: =IF(H13>0,I13/H13,"Undefined") -> 0.3949 | O13: =IF(AND(H13<=0.005,I13<=0.005,J13<=0.005),"Not started",IF(OR(ISTEXT(M13),ISTEXT(N13)),"Insufficient data",IF(MIN(M13,N13)<Settings!$B$3,"Critical",IF(MIN(M13,N13)<Settings!$B$2,"Warning","Favourable")))) -> Critical
... A21: =Inputs!A21 -> 5 | B21: =Inputs!B21 -> 41698 | C21: =Inputs!C21 -> WP4 | D21: =Inputs!D21 -> Finishing: street furniture and signage | E21: =Inputs!E21 -> 28803.68 | F21: =Inputs!F21 -> 100 | G21: =Inputs!G21 -> 100 | H21: =E21*F21/100 -> 28803.68 | I21: =E21*G21/100 -> 28803.68 | J21: =Inputs!H21 -> 26779.64 | K21: =I21-J21 -> 2024.04 | L21: =I21-H21 -> 0 | M21: =IF(J21>0,I21/J21,"Undefined") -> 1.0755813 | N21: =IF(H21>0,I21/H21,"Undefined") -> 1 | O21: =IF(AND(H21<=0.005,I21<=0.005,J21<=0.005),"Not started",IF(OR(ISTEXT(M21),ISTEXT(N21)),"Insufficient data",IF(MIN(M21,N21)<Settings!$B$3,"Critical",IF(MIN(M21,N21)<Settings!$B$2,"Warning","Favourable")))) -> Favourable

Sheet Project calculation
A1: Period | B1: Status date | C1: BAC | D1: PV | E1: EV | F1: AC | G1: CV | H1: SV | I1: CPI | J1: SPI | K1: % planned | L1: % complete | M1: % spent | N1: EAC A | O1: EAC B | P1: EAC C | Q1: ETC A | R1: ETC B | S1: ETC C | T1: VAC A | U1: VAC B | V1: VAC C | W1: Overrun % A | X1: TCPI to BAC | Y1: TCPI to EAC A | Z1: TCPI to EAC B | AA1: TCPI to EAC C | AB1: CPI status | AC1: SPI status | AD1: Overrun status (A) | AE1: Overall health (method A)
A2: 1 | B2: =INDEX('Work package calculation'!$B$2:$B$21,MATCH(A2,'Work package calculation'!$A$2:$A$21,0)) -> 41578 | C2: =SUMIFS('Work package calculation'!$E$2:$E$21,'Work package calculation'!$A$2:$A$21,A2) -> 214417.71 | D2: =SUMIFS('Work package calculation'!$H$2:$H$21,'Work package calculation'!$A$2:$A$21,A2) -> 61225.574 | E2: =SUMIFS('Work package calculation'!$I$2:$I$21,'Work package calculation'!$A$2:$A$21,A2) -> 33297.096 | F2: =SUMIFS('Work package calculation'!$J$2:$J$21,'Work package calculation'!$A$2:$A$21,A2) -> 29324.18 | G2: =E2-F2 -> 3972.9163 | H2: =E2-D2 -> -27928.478 | I2: =IF(F2>0,E2/F2,"Undefined") -> 1.1354826 | J2: =IF(D2>0,E2/D2,"Undefined") -> 0.54384294 | K2: =D2/C2*100 -> 28.554346 | L2: =E2/C2*100 -> 15.529079 | M2: =F2/C2*100 -> 13.676193 | N2: =IF(ISNUMBER(I2),IF(I2>0,C2/I2,"Undefined"),"Undefined") -> 188833.99 | O2: =IF(AND(ISNUMBER(I2),ISNUMBER(J2)),IF(I2*J2>0,F2+(C2-E2)/(I2*J2),"Undefined"),"Undefined") -> 322625.42 | P2: =F2+C2-E2 -> 210444.79 | Q2: =IF(ISNUMBER(N2),N2-F2,N2) -> 159509.81 | R2: =IF(ISNUMBER(O2),O2-F2,O2) -> 293301.24 | S2: =IF(ISNUMBER(P2),P2-F2,P2) -> 181120.61 | T2: =IF(ISNUMBER(N2),C2-N2,N2) -> 25583.721 | U2: =IF(ISNUMBER(O2),C2-O2,O2) -> -108207.71 | V2: =IF(ISNUMBER(P2),C2-P2,P2) -> 3972.9163 | W2: =IF(ISNUMBER(N2),(N2-C2)/C2*100,N2) -> -11.93172 | X2: =IF(C2-E2<0.000000001,"N/A",IF(C2-F2<0.000000001,"Undefined",(C2-E2)/(C2-F2))) -> 0.97853563 | Y2: =IF(C2-E2<0.000000001,"N/A",IF(NOT(ISNUMBER(N2)),"Undefined",IF(N2-F2<0.000000001,"Undefined",(C2-E2)/(N2-F2)))) -> 1.1354826 | Z2: =IF(C2-E2<0.000000001,"N/A",IF(NOT(ISNUMBER(O2)),"Undefined",IF(O2-F2<0.000000001,"Undefined",(C2-E2)/(O2-F2)))) -> 0.6175242 | AA2: =IF(C2-E2<0.000000001,"N/A",IF(NOT(ISNUMBER(P2)),"Undefined",IF(P2-F2<0.000000001,"Undefined",(C2-E2)/(P2-F2)))) -> 1 | AB2: =IF(ISNUMBER(I2),IF(I2<Settings!$B$3,"Critical",IF(I2<Settings!$B$2,"Warning","Favourable")),"Insufficient data") -> Favourable | AC2: =IF(ISNUMBER(J2),IF(J2<Settings!$B$3,"Critical",IF(J2<Settings!$B$2,"Warning","Favourable")),"Insufficient data") -> Critical | AD2: =IF(ISNUMBER(W2),IF(W2>Settings!$B$5,"Critical",IF(W2>Settings!$B$4,"Warning","Favourable")),"Insufficient data") -> Favourable | AE2: =IF(OR(AB2="Critical",AC2="Critical",AD2="Critical"),"Critical",IF(OR(AB2="Insufficient data",AC2="Insufficient data",AD2="Insufficient data"),"Insufficient data",IF(OR(AB2="Warning",AC2="Warning",AD2="Warning"),"Warning","Favourable"))) -> Critical
A3: 2 | B3: =INDEX('Work package calculation'!$B$2:$B$21,MATCH(A3,'Work package calculation'!$A$2:$A$21,0)) -> 41608 | C3: =SUMIFS('Work package calculation'!$E$2:$E$21,'Work package calculation'!$A$2:$A$21,A3) -> 214417.71 | D3: =SUMIFS('Work package calculation'!$H$2:$H$21,'Work package calculation'!$A$2:$A$21,A3) -> 111762.84 | E3: =SUMIFS('Work package calculation'!$I$2:$I$21,'Work package calculation'!$A$2:$A$21,A3) -> 79787.407 | F3: =SUMIFS('Work package calculation'!$J$2:$J$21,'Work package calculation'!$A$2:$A$21,A3) -> 105692.27 | G3: =E3-F3 -> -25904.863 | H3: =E3-D3 -> -31975.433 | I3: =IF(F3>0,E3/F3,"Undefined") -> 0.75490296 | J3: =IF(D3>0,E3/D3,"Undefined") -> 0.71389924 | K3: =D3/C3*100 -> 52.123885 | L3: =E3/C3*100 -> 37.211202 | M3: =F3/C3*100 -> 49.292696 | N3: =IF(ISNUMBER(I3),IF(I3>0,C3/I3,"Undefined"),"Undefined") -> 284033.47 | O3: =IF(AND(ISNUMBER(I3),ISNUMBER(J3)),IF(I3*J3>0,F3+(C3-E3)/(I3*J3),"Undefined"),"Undefined") -> 355505.12 | P3: =F3+C3-E3 -> 240322.57 | Q3: =IF(ISNUMBER(N3),N3-F3,N3) -> 178341.2 | R3: =IF(ISNUMBER(O3),O3-F3,O3) -> 249812.85 | S3: =IF(ISNUMBER(P3),P3-F3,P3) -> 134630.3 | T3: =IF(ISNUMBER(N3),C3-N3,N3) -> -69615.765 | U3: =IF(ISNUMBER(O3),C3-O3,O3) -> -141087.41 | V3: =IF(ISNUMBER(P3),C3-P3,P3) -> -25904.863 | W3: =IF(ISNUMBER(N3),(N3-C3)/C3*100,N3) -> 32.467358 | X3: =IF(C3-E3<0.000000001,"N/A",IF(C3-F3<0.000000001,"Undefined",(C3-E3)/(C3-F3))) -> 1.2382594 | Y3: =IF(C3-E3<0.000000001,"N/A",IF(NOT(ISNUMBER(N3)),"Undefined",IF(N3-F3<0.000000001,"Undefined",(C3-E3)/(N3-F3)))) -> 0.75490296 | Z3: =IF(C3-E3<0.000000001,"N/A",IF(NOT(ISNUMBER(O3)),"Undefined",IF(O3-F3<0.000000001,"Undefined",(C3-E3)/(O3-F3)))) -> 0.53892465 | AA3: =IF(C3-E3<0.000000001,"N/A",IF(NOT(ISNUMBER(P3)),"Undefined",IF(P3-F3<0.000000001,"Undefined",(C3-E3)/(P3-F3)))) -> 1 | AB3: =IF(ISNUMBER(I3),IF(I3<Settings!$B$3,"Critical",IF(I3<Settings!$B$2,"Warning","Favourable")),"Insufficient data") -> Critical | AC3: =IF(ISNUMBER(J3),IF(J3<Settings!$B$3,"Critical",IF(J3<Settings!$B$2,"Warning","Favourable")),"Insufficient data") -> Critical | AD3: =IF(ISNUMBER(W3),IF(W3>Settings!$B$5,"Critical",IF(W3>Settings!$B$4,"Warning","Favourable")),"Insufficient data") -> Critical | AE3: =IF(OR(AB3="Critical",AC3="Critical",AD3="Critical"),"Critical",IF(OR(AB3="Insufficient data",AC3="Insufficient data",AD3="Insufficient data"),"Insufficient data",IF(OR(AB3="Warning",AC3="Warning",AD3="Warning"),"Warning","Favourable"))) -> Critical
A4: 3 | B4: =INDEX('Work package calculation'!$B$2:$B$21,MATCH(A4,'Work package calculation'!$A$2:$A$21,0)) -> 41639 | C4: =SUMIFS('Work package calculation'!$E$2:$E$21,'Work package calculation'!$A$2:$A$21,A4) -> 214417.71 | D4: =SUMIFS('Work package calculation'!$H$2:$H$21,'Work package calculation'!$A$2:$A$21,A4) -> 214417.71 | E4: =SUMIFS('Work package calculation'!$I$2:$I$21,'Work package calculation'!$A$2:$A$21,A4) -> 111728.57 | F4: =SUMIFS('Work package calculation'!$J$2:$J$21,'Work package calculation'!$A$2:$A$21,A4) -> 156594.45 | G4: =E4-F4 -> -44865.879 | H4: =E4-D4 -> -102689.14 | I4: =IF(F4>0,E4/F4,"Undefined") -> 0.71348998 | J4: =IF(D4>0,E4/D4,"Undefined") -> 0.52107902 | K4: =D4/C4*100 -> 100 | L4: =E4/C4*100 -> 52.107902 | M4: =F4/C4*100 -> 73.032423 | N4: =IF(ISNUMBER(I4),IF(I4>0,C4/I4,"Undefined"),"Undefined") -> 300519.58 | O4: =IF(AND(ISNUMBER(I4),ISNUMBER(J4)),IF(I4*J4>0,F4+(C4-E4)/(I4*J4),"Undefined"),"Undefined") -> 432800.41 | P4: =F4+C4-E4 -> 259283.59 | Q4: =IF(ISNUMBER(N4),N4-F4,N4) -> 143925.13 | R4: =IF(ISNUMBER(O4),O4-F4,O4) -> 276205.96 | S4: =IF(ISNUMBER(P4),P4-F4,P4) -> 102689.14 | T4: =IF(ISNUMBER(N4),C4-N4,N4) -> -86101.872 | U4: =IF(ISNUMBER(O4),C4-O4,O4) -> -218382.7 | V4: =IF(ISNUMBER(P4),C4-P4,P4) -> -44865.879 | W4: =IF(ISNUMBER(N4),(N4-C4)/C4*100,N4) -> 40.156138 | X4: =IF(C4-E4<0.000000001,"N/A",IF(C4-F4<0.000000001,"Undefined",(C4-E4)/(C4-F4))) -> 1.775914 | Y4: =IF(C4-E4<0.000000001,"N/A",IF(NOT(ISNUMBER(N4)),"Undefined",IF(N4-F4<0.000000001,"Undefined",(C4-E4)/(N4-F4)))) -> 0.71348998 | Z4: =IF(C4-E4<0.000000001,"N/A",IF(NOT(ISNUMBER(O4)),"Undefined",IF(O4-F4<0.000000001,"Undefined",(C4-E4)/(O4-F4)))) -> 0.37178466 | AA4: =IF(C4-E4<0.000000001,"N/A",IF(NOT(ISNUMBER(P4)),"Undefined",IF(P4-F4<0.000000001,"Undefined",(C4-E4)/(P4-F4)))) -> 1 | AB4: =IF(ISNUMBER(I4),IF(I4<Settings!$B$3,"Critical",IF(I4<Settings!$B$2,"Warning","Favourable")),"Insufficient data") -> Critical | AC4: =IF(ISNUMBER(J4),IF(J4<Settings!$B$3,"Critical",IF(J4<Settings!$B$2,"Warning","Favourable")),"Insufficient data") -> Critical | AD4: =IF(ISNUMBER(W4),IF(W4>Settings!$B$5,"Critical",IF(W4>Settings!$B$4,"Warning","Favourable")),"Insufficient data") -> Critical | AE4: =IF(OR(AB4="Critical",AC4="Critical",AD4="Critical"),"Critical",IF(OR(AB4="Insufficient data",AC4="Insufficient data",AD4="Insufficient data"),"Insufficient data",IF(OR(AB4="Warning",AC4="Warning",AD4="Warning"),"Warning","Favourable"))) -> Critical
A5: 4 | B5: =INDEX('Work package calculation'!$B$2:$B$21,MATCH(A5,'Work package calculation'!$A$2:$A$21,0)) -> 41670 | C5: =SUMIFS('Work package calculation'!$E$2:$E$21,'Work package calculation'!$A$2:$A$21,A5) -> 214417.71 | D5: =SUMIFS('Work package calculation'!$H$2:$H$21,'Work package calculation'!$A$2:$A$21,A5) -> 214417.71 | E5: =SUMIFS('Work package calculation'!$I$2:$I$21,'Work package calculation'!$A$2:$A$21,A5) -> 190584.14 | F5: =SUMIFS('Work package calculation'!$J$2:$J$21,'Work package calculation'!$A$2:$A$21,A5) -> 194759.6 | G5: =E5-F5 -> -4175.4605 | H5: =E5-D5 -> -23833.57 | I5: =IF(F5>0,E5/F5,"Undefined") -> 0.97856095 | J5: =IF(D5>0,E5/D5,"Undefined") -> 0.88884514 | K5: =D5/C5*100 -> 100 | L5: =E5/C5*100 -> 88.884514 | M5: =F5/C5*100 -> 90.831863 | N5: =IF(ISNUMBER(I5),IF(I5>0,C5/I5,"Undefined"),"Undefined") -> 219115.33 | O5: =IF(AND(ISNUMBER(I5),ISNUMBER(J5)),IF(I5*J5>0,F5+(C5-E5)/(I5*J5),"Undefined"),"Undefined") -> 222161.15 | P5: =F5+C5-E5 -> 218593.17 | Q5: =IF(ISNUMBER(N5),N5-F5,N5) -> 24355.734 | R5: =IF(ISNUMBER(O5),O5-F5,O5) -> 27401.55 | S5: =IF(ISNUMBER(P5),P5-F5,P5) -> 23833.57 | T5: =IF(ISNUMBER(N5),C5-N5,N5) -> -4697.6242 | U5: =IF(ISNUMBER(O5),C5-O5,O5) -> -7743.4396 | V5: =IF(ISNUMBER(P5),C5-P5,P5) -> -4175.4605 | W5: =IF(ISNUMBER(N5),(N5-C5)/C5*100,N5) -> 2.1908751 | X5: =IF(C5-E5<0.000000001,"N/A",IF(C5-F5<0.000000001,"Undefined",(C5-E5)/(C5-F5))) -> 1.212404 | Y5: =IF(C5-E5<0.000000001,"N/A",IF(NOT(ISNUMBER(N5)),"Undefined",IF(N5-F5<0.000000001,"Undefined",(C5-E5)/(N5-F5)))) -> 0.97856095 | Z5: =IF(C5-E5<0.000000001,"N/A",IF(NOT(ISNUMBER(O5)),"Undefined",IF(O5-F5<0.000000001,"Undefined",(C5-E5)/(O5-F5)))) -> 0.86978915 | AA5: =IF(C5-E5<0.000000001,"N/A",IF(NOT(ISNUMBER(P5)),"Undefined",IF(P5-F5<0.000000001,"Undefined",(C5-E5)/(P5-F5)))) -> 1 | AB5: =IF(ISNUMBER(I5),IF(I5<Settings!$B$3,"Critical",IF(I5<Settings!$B$2,"Warning","Favourable")),"Insufficient data") -> Warning | AC5: =IF(ISNUMBER(J5),IF(J5<Settings!$B$3,"Critical",IF(J5<Settings!$B$2,"Warning","Favourable")),"Insufficient data") -> Critical | AD5: =IF(ISNUMBER(W5),IF(W5>Settings!$B$5,"Critical",IF(W5>Settings!$B$4,"Warning","Favourable")),"Insufficient data") -> Warning | AE5: =IF(OR(AB5="Critical",AC5="Critical",AD5="Critical"),"Critical",IF(OR(AB5="Insufficient data",AC5="Insufficient data",AD5="Insufficient data"),"Insufficient data",IF(OR(AB5="Warning",AC5="Warning",AD5="Warning"),"Warning","Favourable"))) -> Critical
A6: 5 | B6: =INDEX('Work package calculation'!$B$2:$B$21,MATCH(A6,'Work package calculation'!$A$2:$A$21,0)) -> 41698 | C6: =SUMIFS('Work package calculation'!$E$2:$E$21,'Work package calculation'!$A$2:$A$21,A6) -> 214417.71 | D6: =SUMIFS('Work package calculation'!$H$2:$H$21,'Work package calculation'!$A$2:$A$21,A6) -> 214417.71 | E6: =SUMIFS('Work package calculation'!$I$2:$I$21,'Work package calculation'!$A$2:$A$21,A6) -> 214417.71 | F6: =SUMIFS('Work package calculation'!$J$2:$J$21,'Work package calculation'!$A$2:$A$21,A6) -> 224789.67 | G6: =E6-F6 -> -10371.96 | H6: =E6-D6 -> 0 | I6: =IF(F6>0,E6/F6,"Undefined") -> 0.95385927 | J6: =IF(D6>0,E6/D6,"Undefined") -> 1 | K6: =D6/C6*100 -> 100 | L6: =E6/C6*100 -> 100 | M6: =F6/C6*100 -> 104.83727 | N6: =IF(ISNUMBER(I6),IF(I6>0,C6/I6,"Undefined"),"Undefined") -> 224789.67 | O6: =IF(AND(ISNUMBER(I6),ISNUMBER(J6)),IF(I6*J6>0,F6+(C6-E6)/(I6*J6),"Undefined"),"Undefined") -> 224789.67 | P6: =F6+C6-E6 -> 224789.67 | Q6: =IF(ISNUMBER(N6),N6-F6,N6) -> 0 | R6: =IF(ISNUMBER(O6),O6-F6,O6) -> 0 | S6: =IF(ISNUMBER(P6),P6-F6,P6) -> 0 | T6: =IF(ISNUMBER(N6),C6-N6,N6) -> -10371.96 | U6: =IF(ISNUMBER(O6),C6-O6,O6) -> -10371.96 | V6: =IF(ISNUMBER(P6),C6-P6,P6) -> -10371.96 | W6: =IF(ISNUMBER(N6),(N6-C6)/C6*100,N6) -> 4.8372683 | X6: =IF(C6-E6<0.000000001,"N/A",IF(C6-F6<0.000000001,"Undefined",(C6-E6)/(C6-F6))) -> N/A | Y6: =IF(C6-E6<0.000000001,"N/A",IF(NOT(ISNUMBER(N6)),"Undefined",IF(N6-F6<0.000000001,"Undefined",(C6-E6)/(N6-F6)))) -> N/A | Z6: =IF(C6-E6<0.000000001,"N/A",IF(NOT(ISNUMBER(O6)),"Undefined",IF(O6-F6<0.000000001,"Undefined",(C6-E6)/(O6-F6)))) -> N/A | AA6: =IF(C6-E6<0.000000001,"N/A",IF(NOT(ISNUMBER(P6)),"Undefined",IF(P6-F6<0.000000001,"Undefined",(C6-E6)/(P6-F6)))) -> N/A | AB6: =IF(ISNUMBER(I6),IF(I6<Settings!$B$3,"Critical",IF(I6<Settings!$B$2,"Warning","Favourable")),"Insufficient data") -> Warning | AC6: =IF(ISNUMBER(J6),IF(J6<Settings!$B$3,"Critical",IF(J6<Settings!$B$2,"Warning","Favourable")),"Insufficient data") -> Favourable | AD6: =IF(ISNUMBER(W6),IF(W6>Settings!$B$5,"Critical",IF(W6>Settings!$B$4,"Warning","Favourable")),"Insufficient data") -> Warning | AE6: =IF(OR(AB6="Critical",AC6="Critical",AD6="Critical"),"Critical",IF(OR(AB6="Insufficient data",AC6="Insufficient data",AD6="Insufficient data"),"Insufficient data",IF(OR(AB6="Warning",AC6="Warning",AD6="Warning"),"Warning","Favourable"))) -> Warning

Sheet Forecast check
A1: Period | B1: Status date | C1: % complete | D1: EAC A | E1: EAC B | F1: EAC C | G1: Actual final cost | H1: Error A | I1: Error B | J1: Error C
A2: ='Project calculation'!A2 -> 1 | B2: ='Project calculation'!B2 -> 41578 | C2: ='Project calculation'!L2 -> 15.529079 | D2: ='Project calculation'!N2 -> 188833.99 | E2: ='Project calculation'!O2 -> 322625.42 | F2: ='Project calculation'!P2 -> 210444.79 | G2: =Settings!$B$6 -> 224789.67 | H2: =IF(ISNUMBER(D2),D2/G2-1,D2) -> -0.15995255 | I2: =IF(ISNUMBER(E2),E2/G2-1,E2) -> 0.4352324 | J2: =IF(ISNUMBER(F2),F2/G2-1,F2) -> -0.06381466
A3: ='Project calculation'!A3 -> 2 | B3: ='Project calculation'!B3 -> 41608 | C3: ='Project calculation'!L3 -> 37.211202 | D3: ='Project calculation'!N3 -> 284033.47 | E3: ='Project calculation'!O3 -> 355505.12 | F3: ='Project calculation'!P3 -> 240322.57 | G3: =Settings!$B$6 -> 224789.67 | H3: =IF(ISNUMBER(D3),D3/G3-1,D3) -> 0.26355217 | I3: =IF(ISNUMBER(E3),E3/G3-1,E3) -> 0.58150114 | J3: =IF(ISNUMBER(F3),F3/G3-1,F3) -> 0.069099718
A4: ='Project calculation'!A4 -> 3 | B4: ='Project calculation'!B4 -> 41639 | C4: ='Project calculation'!L4 -> 52.107902 | D4: ='Project calculation'!N4 -> 300519.58 | E4: ='Project calculation'!O4 -> 432800.41 | F4: ='Project calculation'!P4 -> 259283.59 | G4: =Settings!$B$6 -> 224789.67 | H4: =IF(ISNUMBER(D4),D4/G4-1,D4) -> 0.33689231 | I4: =IF(ISNUMBER(E4),E4/G4-1,E4) -> 0.9253572 | J4: =IF(ISNUMBER(F4),F4/G4-1,F4) -> 0.15344975
A5: ='Project calculation'!A5 -> 4 | B5: ='Project calculation'!B5 -> 41670 | C5: ='Project calculation'!L5 -> 88.884514 | D5: ='Project calculation'!N5 -> 219115.33 | E5: ='Project calculation'!O5 -> 222161.15 | F5: ='Project calculation'!P5 -> 218593.17 | G5: =Settings!$B$6 -> 224789.67 | H5: =IF(ISNUMBER(D5),D5/G5-1,D5) -> -0.025242867 | I5: =IF(ISNUMBER(E5),E5/G5-1,E5) -> -0.011693244 | J5: =IF(ISNUMBER(F5),F5/G5-1,F5) -> -0.027565766
A6: ='Project calculation'!A6 -> 5 | B6: ='Project calculation'!B6 -> 41698 | C6: ='Project calculation'!L6 -> 100 | D6: ='Project calculation'!N6 -> 224789.67 | E6: ='Project calculation'!O6 -> 224789.67 | F6: ='Project calculation'!P6 -> 224789.67 | G6: =Settings!$B$6 -> 224789.67 | H6: =IF(ISNUMBER(D6),D6/G6-1,D6) -> 0 | I6: =IF(ISNUMBER(E6),E6/G6-1,E6) -> 0 | J6: =IF(ISNUMBER(F6),F6/G6-1,F6) -> 0
A8: Error = forecast / actual final cost - 1. Negative = the method under-forecast the final cost. Read row 4 (31-Dec-2013, about 52 % complete) as 'what would we have predicted half way?'

Sheet Feature tour
A1: Feature | B1: Reporting date to select | C1: What to show / explain
A2: Home screen and upload | B2: - | C2: Upload the CSV, or press 'Manual check case' on the home screen. The smart reader shows the data type it detected and the column matches.
A3: Signboard and KPI cards | B3: 31 Oct 2013 | C3: CPI 1.135 (cost favourable) but SPI 0.544 (behind schedule) -> Critical.
A4: Not started / early start | B4: 31 Oct 2013 and 30 Nov 2013 | C4: 31 Oct: WP3 and WP4 'Not started'. 30 Nov: WP4 has progress before any work was planned (PV = 0), so its SPI is undefined -> 'Insufficient data' (never shown as 0).
A5: Top problem activities | B5: 30 Nov 2013 | C5: WP2 Earthworks and foundations: AC far above EV (CPI about 0.37).
A6: CPI and SPI trend (combined chart) | B6: 28 Feb 2014 | C6: CPI falls from 1.14 to 0.71 and recovers to 0.95; SPI recovers to 1.00 at completion although the project was 2 months late (SPI limitation).
A7: S-curve | B7: any | C7: PV reaches BAC on 20 Dec 2013 (baseline finish); EV and AC continue to 28 Feb 2014.
A8: Forecasts A, B, C | B8: 31 Dec 2013 | C8: Half way (52 % complete): compare EAC A, B, C with the real final cost EUR 224,789.67 (sheet 'Forecast check').
A9: Method D (independent ETC) | B9: 31 Dec 2013 | C9: Forecasts tab: enter an ETC; the EAC equals AC + ETC (Settings B8).
A10: TCPI | B10: 31 Dec 2013 and 28 Feb 2014 | C10: 31 Dec: efficiency needed to finish on budget. 28 Feb: EV = BAC, so TCPI does not apply (shown as N/A).
A11: Health thresholds | B11: any | C11: Change 'CPI/SPI critical below' in the sidebar and in Settings B3: both update.
A12: Commentary and exports | B12: any | C12: Commentary tab text; Data tab downloads (CSV, Excel workbook).

Sheet Settings
A1: Setting | B1: Value | C1: Note
A2: CPI/SPI warning below | B2: 1 | C2: Dashboard default (sidebar: Health screening thresholds)
A3: CPI/SPI critical below | B3: 0.9 | C3: Dashboard default
A4: Forecast overrun warning above (%) | B4: 0 | C4: Dashboard default
A5: Forecast overrun critical above (%) | B5: 10 | C5: Dashboard default
A6: Actual final cost (AC at completion, 28-Feb-2014) | B6: ='Project calculation'!F6 -> 224789.67 | C6: Known only because the project is finished; used in 'Forecast check'
A7: Method D: independent ETC you want to test (enter a number) | C7: Example: type a bottom-up estimate of the remaining cost at 31-Dec-2013
A8: Method D: EAC = AC (31-Dec-2013) + independent ETC | B8: =IF(ISNUMBER(B7),'Project calculation'!F4+B7,"Enter an ETC in B7") -> Enter an ETC in B7 | C8: Compare with the dashboard: Forecasts tab > Independent estimate, date 31 Dec 2013
